uqc_client/__init__.py
uqc_client/_version.py
uqc_client/plot.py
uqc_client/uqc.py
uqc_client/uqc_backend.py
uqc_client/uqc_config.py
uqc_client/uqc_interfaces.py
uqc_client/utils.py
uqc_client/validator.py
uqc_client-0.1.0.dist-info/METADATA
uqc_client-0.1.0.dist-info/WHEEL
uqc_client-0.1.0.dist-info/top_level.txt
uqc_client-0.1.0.dist-info/RECORD
