Metadata-Version: 2.4
Name: uqc_client
Version: 0.1.0
Summary: Client package for UQC platform apis.
Author-email: mqiezi <mqiezi@qq.com>
Keywords: qiskit,client,ion trap,quantum
Requires-Python: >=3.9
Requires-Dist: aiohttp~=3.11.13
Requires-Dist: aiofiles~=24.1.0
Requires-Dist: importlib-metadata>=8.6.1
Requires-Dist: ipython>=9.4.0; python_version >= "3.11"
Requires-Dist: ipython<9.0; python_version < "3.11"
Requires-Dist: matplotlib>=3.5
Requires-Dist: nest-asyncio>=1.6.0
Requires-Dist: openqasm3~=1.0.1
Requires-Dist: pandas>=2.2.3
Requires-Dist: pydantic~=2.11.4
Requires-Dist: pydantic-extra-types~=2.10.3
Requires-Dist: pydantic-settings~=2.9.1
Requires-Dist: pylatexenc~=2.10
Requires-Dist: python-socketio~=5.12.1
Requires-Dist: qiskit<3.0.0,>=2.0.0
Requires-Dist: qiskit-aer>=0.17.0
Requires-Dist: qiskit-qasm3-import~=0.6.0
Requires-Dist: pytz>=2023.1
Requires-Dist: pyjwt>=2.10.1
Provides-Extra: dev
Requires-Dist: pytest~=7.2.0; extra == "dev"
Requires-Dist: pytest-cov~=4.0.0; extra == "dev"
Requires-Dist: pytest-mock~=3.12.0; extra == "dev"
